MEArec/__init__.py
MEArec/cli.py
MEArec/drift_tools.py
MEArec/generation_tools.py
MEArec/simulate_cells.py
MEArec/tools.py
MEArec/cell_models/bbp/L5_BP_bAC217_1/CHANGELOG
MEArec/cell_models/bbp/L5_BP_bAC217_1/LICENSE
MEArec/cell_models/bbp/L5_BP_bAC217_1/README
MEArec/cell_models/bbp/L5_BP_bAC217_1/VERSION
MEArec/cell_models/bbp/L5_BP_bAC217_1/biophysics.hoc
MEArec/cell_models/bbp/L5_BP_bAC217_1/cellinfo.json
MEArec/cell_models/bbp/L5_BP_bAC217_1/constants.hoc
MEArec/cell_models/bbp/L5_BP_bAC217_1/creategui.hoc
MEArec/cell_models/bbp/L5_BP_bAC217_1/createsimulation.hoc
MEArec/cell_models/bbp/L5_BP_bAC217_1/current_amps.dat
MEArec/cell_models/bbp/L5_BP_bAC217_1/init.hoc
MEArec/cell_models/bbp/L5_BP_bAC217_1/morphology.hoc
MEArec/cell_models/bbp/L5_BP_bAC217_1/mosinit.hoc
MEArec/cell_models/bbp/L5_BP_bAC217_1/ringplot.hoc
MEArec/cell_models/bbp/L5_BP_bAC217_1/run.py
MEArec/cell_models/bbp/L5_BP_bAC217_1/run_RmpRiTau.py
MEArec/cell_models/bbp/L5_BP_bAC217_1/run_RmpRiTau_py.sh
MEArec/cell_models/bbp/L5_BP_bAC217_1/run_hoc.sh
MEArec/cell_models/bbp/L5_BP_bAC217_1/run_py.sh
MEArec/cell_models/bbp/L5_BP_bAC217_1/template.hoc
MEArec/cell_models/bbp/L5_BP_bAC217_1/mechanisms/Ca.mod
MEArec/cell_models/bbp/L5_BP_bAC217_1/mechanisms/CaDynamics_E2.mod
MEArec/cell_models/bbp/L5_BP_bAC217_1/mechanisms/Ca_LVAst.mod
MEArec/cell_models/bbp/L5_BP_bAC217_1/mechanisms/Ih.mod
MEArec/cell_models/bbp/L5_BP_bAC217_1/mechanisms/Im.mod
MEArec/cell_models/bbp/L5_BP_bAC217_1/mechanisms/K_Pst.mod
MEArec/cell_models/bbp/L5_BP_bAC217_1/mechanisms/K_Tst.mod
MEArec/cell_models/bbp/L5_BP_bAC217_1/mechanisms/NaTa_t.mod
MEArec/cell_models/bbp/L5_BP_bAC217_1/mechanisms/NaTs2_t.mod
MEArec/cell_models/bbp/L5_BP_bAC217_1/mechanisms/Nap_Et2.mod
MEArec/cell_models/bbp/L5_BP_bAC217_1/mechanisms/ProbAMPANMDA_EMS.mod
MEArec/cell_models/bbp/L5_BP_bAC217_1/mechanisms/ProbGABAAB_EMS.mod
MEArec/cell_models/bbp/L5_BP_bAC217_1/mechanisms/SK_E2.mod
MEArec/cell_models/bbp/L5_BP_bAC217_1/mechanisms/SKv3_1.mod
MEArec-1.9.2.dist-info/LICENSE
MEArec-1.9.2.dist-info/METADATA
MEArec-1.9.2.dist-info/WHEEL
MEArec-1.9.2.dist-info/entry_points.txt
MEArec-1.9.2.dist-info/top_level.txt
MEArec-1.9.2.dist-info/RECORD
