Metadata-Version: 2.2
Name: MEArec
Version: 1.9.2
Summary: Python toolkit for biophysical simulation of extracellular electrophysiology recordings
Author-email: Alessio Buccino <alessiop.buccino@gmail.com>
Project-URL: homepage, https://github.com/SpikeInterface/MEArec
Project-URL: repository, https://github.com/SpikeInterface/MEArec
Project-URL: documentation, https://mearec.readthedocs.io/
Classifier: Programming Language :: Python :: 3 :: Only
Classifier: License :: OSI Approved :: MIT License
Classifier: Intended Audience :: Science/Research
Classifier: Operating System :: POSIX :: Linux
Classifier: Operating System :: Microsoft :: Windows
Classifier: Operating System :: MacOS
Classifier: Operating System :: OS Independent
Requires-Python: <4.0,>=3.7
License-File: LICENSE
Requires-Dist: numpy
Requires-Dist: matplotlib
Requires-Dist: click
Requires-Dist: pyyaml
Requires-Dist: h5py
Requires-Dist: joblib
Requires-Dist: scipy
Requires-Dist: elephant
Requires-Dist: lazy_ops
Requires-Dist: MEAutility
Provides-Extra: templates
Requires-Dist: neuron; extra == "templates"
Requires-Dist: LFPy; extra == "templates"
Provides-Extra: test
Requires-Dist: pytest; extra == "test"
Requires-Dist: pytest-cov; extra == "test"
